ScrapEvent/ScrapEvent.py
ScrapEvent/__init__.py
ScrapEvent/app.py
bookanevents-0.0.5.dist-info/LICENSE
bookanevents-0.0.5.dist-info/METADATA
bookanevents-0.0.5.dist-info/WHEEL
bookanevents-0.0.5.dist-info/top_level.txt
bookanevents-0.0.5.dist-info/RECORD
